ai_guard/__init__.py
ai_guard/config.py
ai_guard/evaluator.py
ai_guard_dbp-0.2.dist-info/METADATA
ai_guard_dbp-0.2.dist-info/WHEEL
ai_guard_dbp-0.2.dist-info/top_level.txt
ai_guard_dbp-0.2.dist-info/RECORD
