Metadata-Version: 2.2
Name: ai_guard_dbp
Version: 0.2
Summary: A module for applying evaluation metrics and guardrails to queries and generated responses.
Author: Dipak Balram Patil
Author-email: verulikar@gmail.com
Classifier: Programming Language :: Python :: 3
Classifier: License :: OSI Approved :: MIT License
Classifier: Operating System :: OS Independent
Requires-Dist: presidio-analyzer
Requires-Dist: transformers
Requires-Dist: bert-score
Requires-Dist: rouge-score
Requires-Dist: pandas
Dynamic: author
Dynamic: author-email
Dynamic: classifier
Dynamic: description
Dynamic: description-content-type
Dynamic: requires-dist
Dynamic: summary
